ecmind_blue_client_asyncio/__init__.py
ecmind_blue_client_asyncio/blue_client.py
ecmind_blue_client_asyncio/blue_connection_strategy.py
ecmind_blue_client_asyncio/blue_exception.py
ecmind_blue_client_asyncio/blue_server_config.py
ecmind_blue_client_asyncio/call_job_parameters.py
ecmind_blue_client_asyncio/const.py
ecmind_blue_client_asyncio/file_footer.py
ecmind_blue_client_asyncio/file_header.py
ecmind_blue_client_asyncio/job.py
ecmind_blue_client_asyncio/job_caller.py
ecmind_blue_client_asyncio/job_header.py
ecmind_blue_client_asyncio/job_parameter_data.py
ecmind_blue_client_asyncio/job_parameter_description.py
ecmind_blue_client_asyncio/job_parameters.py
ecmind_blue_client_asyncio/job_serializer.py
ecmind_blue_client_asyncio/param.py
ecmind_blue_client_asyncio/result.py
ecmind_blue_client_asyncio/result_file.py
ecmind_blue_client_asyncio-0.0.2.dist-info/METADATA
ecmind_blue_client_asyncio-0.0.2.dist-info/WHEEL
ecmind_blue_client_asyncio-0.0.2.dist-info/top_level.txt
ecmind_blue_client_asyncio-0.0.2.dist-info/RECORD
